{
  "modelVersion" : "2.0",
  "id" : "UpdatePeopleForm",
  "name" : "UpdatePeopleForm",
  "lastUpdate" : 1602163086310,
  "rows" : [
    [
      {
        "type" : "container",
        "dimension" : {
          "xs" : 12
        },
        "propertyValues" : { },
        "reference" : "dfcd9779-9b12-4e9e-bc86-9cac7825c524",
        "hasValidationError" : false,
        "id" : "pbContainer",
        "rows" : [
          [
            {
              "type" : "component",
              "dimension" : {
                "md" : 12,
                "sm" : 12,
                "xs" : 12,
                "lg" : 12
              },
              "propertyValues" : {
                "hidden" : {
                  "type" : "constant",
                  "value" : false
                },
                "level" : {
                  "type" : "constant",
                  "value" : "Level 1"
                },
                "cssClasses" : {
                  "type" : "constant",
                  "value" : ""
                },
                "text" : {
                  "type" : "interpolation",
                  "value" : "{{ task.displayName }}"
                },
                "alignment" : {
                  "type" : "constant",
                  "value" : "center"
                },
                "dimension" : {
                  "type" : "constant",
                  "value" : 12
                }
              },
              "reference" : "c8ef44d4-91e4-4bf7-b819-614d82e9e9ca",
              "hasValidationError" : false,
              "id" : "pbTitle",
              "description" : ""
            }
          ],
          [
            {
              "type" : "component",
              "dimension" : {
                "md" : 12,
                "sm" : 12,
                "xs" : 12,
                "lg" : 12
              },
              "propertyValues" : {
                "allowHtml" : {
                  "type" : "constant",
                  "value" : true
                },
                "labelHidden" : {
                  "type" : "constant",
                  "value" : true
                },
                "hidden" : {
                  "type" : "constant",
                  "value" : false
                },
                "cssClasses" : {
                  "type" : "constant",
                  "value" : ""
                },
                "label" : {
                  "type" : "interpolation"
                },
                "text" : {
                  "type" : "interpolation",
                  "value" : "{{ task.displayDescription }}"
                },
                "alignment" : {
                  "type" : "constant",
                  "value" : "left"
                },
                "dimension" : {
                  "type" : "constant",
                  "value" : 12
                }
              },
              "reference" : "172b5d44-67ba-4ac4-9604-1c6a3f65e093",
              "hasValidationError" : false,
              "id" : "pbText",
              "description" : ""
            }
          ]
        ]
      }
    ],
    [
      {
        "type" : "formContainer",
        "dimension" : {
          "xs" : 12
        },
        "propertyValues" : { },
        "reference" : "e66bc580-62f1-4fc4-bae2-9c21f76787cf",
        "hasValidationError" : false,
        "id" : "pbFormContainer",
        "container" : {
          "type" : "container",
          "dimension" : {
            "xs" : 12
          },
          "propertyValues" : { },
          "reference" : "0d804260-aac5-45f2-b3a1-42e661ad34a5",
          "hasValidationError" : false,
          "id" : "pbContainer",
          "rows" : [
            [
              {
                "type" : "component",
                "dimension" : {
                  "md" : 12,
                  "sm" : 12,
                  "xs" : 12,
                  "lg" : 12
                },
                "propertyValues" : {
                  "hidden" : {
                    "type" : "constant",
                    "value" : false
                  },
                  "level" : {
                    "type" : "constant",
                    "value" : "Level 4"
                  },
                  "cssClasses" : {
                    "type" : "constant",
                    "value" : ""
                  },
                  "text" : {
                    "type" : "interpolation",
                    "value" : "People"
                  },
                  "alignment" : {
                    "type" : "constant",
                    "value" : "left"
                  },
                  "dimension" : {
                    "type" : "constant",
                    "value" : 12
                  }
                },
                "reference" : "55e03610-f87a-4566-8f7c-ba4645b3bd87",
                "hasValidationError" : false,
                "id" : "pbTitle",
                "description" : ""
              }
            ],
            [
              {
                "type" : "container",
                "dimension" : {
                  "md" : 12,
                  "sm" : 12,
                  "xs" : 12,
                  "lg" : 12
                },
                "propertyValues" : {
                  "repeatedCollection" : {
                    "type" : "variable",
                    "value" : ""
                  },
                  "hidden" : {
                    "type" : "constant",
                    "value" : false
                  },
                  "cssClasses" : {
                    "type" : "constant",
                    "value" : ""
                  },
                  "dimension" : {
                    "type" : "constant",
                    "value" : 12
                  }
                },
                "reference" : "7581cd7a-6c80-40ae-a63e-be5fc87b7f52",
                "hasValidationError" : false,
                "id" : "pbContainer",
                "rows" : [
                  [
                    {
                      "type" : "component",
                      "dimension" : {
                        "md" : 12,
                        "sm" : 12,
                        "xs" : 12,
                        "lg" : 12
                      },
                      "propertyValues" : {
                        "labelHidden" : {
                          "type" : "constant",
                          "value" : false
                        },
                        "hidden" : {
                          "type" : "constant",
                          "value" : false
                        },
                        "labelPosition" : {
                          "type" : "constant",
                          "value" : "top"
                        },
                        "cssClasses" : {
                          "type" : "constant",
                          "value" : ""
                        },
                        "labelWidth" : {
                          "type" : "constant",
                          "value" : 1
                        },
                        "readOnly" : {
                          "type" : "constant",
                          "value" : false
                        },
                        "label" : {
                          "type" : "interpolation",
                          "value" : "First Name"
                        },
                        "placeholder" : {
                          "type" : "constant"
                        },
                        "type" : {
                          "type" : "constant",
                          "value" : "text"
                        },
                        "dimension" : {
                          "type" : "constant",
                          "value" : 12
                        },
                        "value" : {
                          "type" : "variable",
                          "value" : "peopleToUpdate.firstName"
                        },
                        "required" : {
                          "type" : "constant",
                          "value" : true
                        }
                      },
                      "reference" : "afbec1e9-2c28-458e-a720-df97586b37e6",
                      "hasValidationError" : false,
                      "id" : "pbInput",
                      "description" : ""
                    }
                  ],
                  [
                    {
                      "type" : "component",
                      "dimension" : {
                        "md" : 12,
                        "sm" : 12,
                        "xs" : 12,
                        "lg" : 12
                      },
                      "propertyValues" : {
                        "labelHidden" : {
                          "type" : "constant",
                          "value" : false
                        },
                        "hidden" : {
                          "type" : "constant",
                          "value" : false
                        },
                        "labelPosition" : {
                          "type" : "constant",
                          "value" : "top"
                        },
                        "cssClasses" : {
                          "type" : "constant",
                          "value" : ""
                        },
                        "labelWidth" : {
                          "type" : "constant",
                          "value" : 1
                        },
                        "readOnly" : {
                          "type" : "constant",
                          "value" : false
                        },
                        "label" : {
                          "type" : "interpolation",
                          "value" : "Last Name"
                        },
                        "placeholder" : {
                          "type" : "constant"
                        },
                        "type" : {
                          "type" : "constant",
                          "value" : "text"
                        },
                        "dimension" : {
                          "type" : "constant",
                          "value" : 12
                        },
                        "value" : {
                          "type" : "variable",
                          "value" : "peopleToUpdate.lastName"
                        },
                        "required" : {
                          "type" : "constant",
                          "value" : true
                        }
                      },
                      "reference" : "dae54bd9-26f3-432a-9c67-d2d454a540e6",
                      "hasValidationError" : false,
                      "id" : "pbInput",
                      "description" : ""
                    }
                  ],
                  [
                    {
                      "type" : "component",
                      "dimension" : {
                        "md" : 12,
                        "sm" : 12,
                        "xs" : 12,
                        "lg" : 12
                      },
                      "propertyValues" : {
                        "hidden" : {
                          "type" : "constant",
                          "value" : false
                        },
                        "dateFormat" : {
                          "type" : "constant",
                          "value" : "MM/dd/yyyy"
                        },
                        "cssClasses" : {
                          "type" : "constant",
                          "value" : ""
                        },
                        "labelWidth" : {
                          "type" : "constant",
                          "value" : 1
                        },
                        "readOnly" : {
                          "type" : "constant",
                          "value" : false
                        },
                        "label" : {
                          "type" : "interpolation",
                          "value" : "Birth Date"
                        },
                        "type" : {
                          "type" : "constant"
                        },
                        "required" : {
                          "type" : "constant",
                          "value" : true
                        },
                        "todayLabel" : {
                          "type" : "constant",
                          "value" : "Today"
                        },
                        "labelHidden" : {
                          "type" : "constant",
                          "value" : false
                        },
                        "showToday" : {
                          "type" : "constant",
                          "value" : true
                        },
                        "labelPosition" : {
                          "type" : "constant",
                          "value" : "top"
                        },
                        "placeholder" : {
                          "type" : "constant",
                          "value" : "Enter a date (mm/dd/yyyy)"
                        },
                        "dimension" : {
                          "type" : "constant",
                          "value" : 12
                        },
                        "value" : {
                          "type" : "variable",
                          "value" : "peopleToUpdate.birthDate"
                        }
                      },
                      "reference" : "7d65c427-d9d4-4905-a6e2-721b4be93f78",
                      "hasValidationError" : false,
                      "id" : "pbDatePicker",
                      "description" : ""
                    }
                  ],
                  [
                    {
                      "type" : "component",
                      "dimension" : {
                        "md" : 12,
                        "sm" : 12,
                        "xs" : 12,
                        "lg" : 12
                      },
                      "propertyValues" : {
                        "hidden" : {
                          "type" : "constant",
                          "value" : false
                        },
                        "level" : {
                          "type" : "constant",
                          "value" : "Level 4"
                        },
                        "cssClasses" : {
                          "type" : "constant",
                          "value" : ""
                        },
                        "text" : {
                          "type" : "interpolation",
                          "value" : "Address"
                        },
                        "alignment" : {
                          "type" : "constant",
                          "value" : "left"
                        },
                        "dimension" : {
                          "type" : "constant",
                          "value" : 12
                        }
                      },
                      "reference" : "d8b9c047-6645-4a81-82d8-c3698d4d2e2a",
                      "hasValidationError" : false,
                      "id" : "pbTitle",
                      "description" : ""
                    }
                  ],
                  [
                    {
                      "type" : "container",
                      "dimension" : {
                        "md" : 12,
                        "sm" : 12,
                        "xs" : 12,
                        "lg" : 12
                      },
                      "propertyValues" : {
                        "repeatedCollection" : {
                          "type" : "variable",
                          "value" : "peopleToUpdate.address"
                        },
                        "hidden" : {
                          "type" : "constant",
                          "value" : false
                        },
                        "cssClasses" : {
                          "type" : "constant",
                          "value" : ""
                        },
                        "dimension" : {
                          "type" : "constant",
                          "value" : 12
                        }
                      },
                      "reference" : "8db79763-6039-4bb7-b0df-a13dfa8a4e30",
                      "hasValidationError" : false,
                      "id" : "pbContainer",
                      "rows" : [
                        [
                          {
                            "type" : "component",
                            "dimension" : {
                              "md" : 12,
                              "sm" : 12,
                              "xs" : 12,
                              "lg" : 12
                            },
                            "propertyValues" : {
                              "labelHidden" : {
                                "type" : "constant",
                                "value" : false
                              },
                              "hidden" : {
                                "type" : "constant",
                                "value" : false
                              },
                              "labelPosition" : {
                                "type" : "constant",
                                "value" : "top"
                              },
                              "cssClasses" : {
                                "type" : "constant",
                                "value" : ""
                              },
                              "labelWidth" : {
                                "type" : "constant",
                                "value" : 1
                              },
                              "readOnly" : {
                                "type" : "constant",
                                "value" : false
                              },
                              "label" : {
                                "type" : "interpolation",
                                "value" : "Street"
                              },
                              "placeholder" : {
                                "type" : "constant"
                              },
                              "type" : {
                                "type" : "constant",
                                "value" : "text"
                              },
                              "dimension" : {
                                "type" : "constant",
                                "value" : 12
                              },
                              "value" : {
                                "type" : "variable",
                                "value" : "$item.street"
                              },
                              "required" : {
                                "type" : "constant",
                                "value" : true
                              }
                            },
                            "reference" : "e66bdfb5-9836-4f5a-884a-270d5e14437e",
                            "hasValidationError" : false,
                            "id" : "pbInput",
                            "description" : ""
                          }
                        ],
                        [
                          {
                            "type" : "component",
                            "dimension" : {
                              "md" : 12,
                              "sm" : 12,
                              "xs" : 12,
                              "lg" : 12
                            },
                            "propertyValues" : {
                              "labelHidden" : {
                                "type" : "constant",
                                "value" : false
                              },
                              "hidden" : {
                                "type" : "constant",
                                "value" : false
                              },
                              "labelPosition" : {
                                "type" : "constant",
                                "value" : "top"
                              },
                              "cssClasses" : {
                                "type" : "constant",
                                "value" : ""
                              },
                              "labelWidth" : {
                                "type" : "constant",
                                "value" : 1
                              },
                              "readOnly" : {
                                "type" : "constant",
                                "value" : false
                              },
                              "label" : {
                                "type" : "interpolation",
                                "value" : "Zipcode"
                              },
                              "placeholder" : {
                                "type" : "constant"
                              },
                              "type" : {
                                "type" : "constant",
                                "value" : "text"
                              },
                              "dimension" : {
                                "type" : "constant",
                                "value" : 12
                              },
                              "value" : {
                                "type" : "variable",
                                "value" : "$item.zipcode"
                              },
                              "required" : {
                                "type" : "constant",
                                "value" : true
                              }
                            },
                            "reference" : "a74cd8a6-8de5-4b33-9d32-ae1506e1343d",
                            "hasValidationError" : false,
                            "id" : "pbInput",
                            "description" : ""
                          }
                        ],
                        [
                          {
                            "type" : "component",
                            "dimension" : {
                              "md" : 12,
                              "sm" : 12,
                              "xs" : 12,
                              "lg" : 12
                            },
                            "propertyValues" : {
                              "labelHidden" : {
                                "type" : "constant",
                                "value" : false
                              },
                              "hidden" : {
                                "type" : "constant",
                                "value" : false
                              },
                              "labelPosition" : {
                                "type" : "constant",
                                "value" : "top"
                              },
                              "cssClasses" : {
                                "type" : "constant",
                                "value" : ""
                              },
                              "labelWidth" : {
                                "type" : "constant",
                                "value" : 1
                              },
                              "readOnly" : {
                                "type" : "constant",
                                "value" : false
                              },
                              "label" : {
                                "type" : "interpolation",
                                "value" : "City"
                              },
                              "placeholder" : {
                                "type" : "constant"
                              },
                              "type" : {
                                "type" : "constant",
                                "value" : "text"
                              },
                              "dimension" : {
                                "type" : "constant",
                                "value" : 12
                              },
                              "value" : {
                                "type" : "variable",
                                "value" : "$item.city"
                              },
                              "required" : {
                                "type" : "constant",
                                "value" : true
                              }
                            },
                            "reference" : "b88be6d7-998d-4549-91f6-3cdee2c079fa",
                            "hasValidationError" : false,
                            "id" : "pbInput",
                            "description" : ""
                          }
                        ],
                        [
                          {
                            "type" : "component",
                            "dimension" : {
                              "md" : 12,
                              "sm" : 12,
                              "xs" : 12,
                              "lg" : 12
                            },
                            "propertyValues" : {
                              "labelHidden" : {
                                "type" : "constant",
                                "value" : false
                              },
                              "hidden" : {
                                "type" : "constant",
                                "value" : false
                              },
                              "labelPosition" : {
                                "type" : "constant",
                                "value" : "top"
                              },
                              "cssClasses" : {
                                "type" : "constant",
                                "value" : ""
                              },
                              "availableValues" : {
                                "type" : "expression",
                                "value" : "country_query"
                              },
                              "labelWidth" : {
                                "type" : "constant",
                                "value" : 1
                              },
                              "label" : {
                                "type" : "interpolation",
                                "value" : "Country"
                              },
                              "placeholder" : {
                                "type" : "constant",
                                "value" : "Select a Country"
                              },
                              "dimension" : {
                                "type" : "constant",
                                "value" : 12
                              },
                              "value" : {
                                "type" : "variable",
                                "value" : "$item.country"
                              },
                              "required" : {
                                "type" : "constant",
                                "value" : true
                              },
                              "disabled" : {
                                "type" : "constant",
                                "value" : false
                              },
                              "displayedKey" : {
                                "type" : "constant",
                                "value" : "name"
                              },
                              "returnedKey" : {
                                "type" : "constant"
                              }
                            },
                            "reference" : "bb20e60c-00fe-4672-86bc-e3d8cbd34f62",
                            "hasValidationError" : false,
                            "id" : "pbSelect",
                            "description" : ""
                          }
                        ],
                        [
                          {
                            "type" : "component",
                            "dimension" : {
                              "md" : 12,
                              "sm" : 12,
                              "xs" : 12,
                              "lg" : 12
                            },
                            "propertyValues" : {
                              "removeItem" : {
                                "type" : "variable",
                                "value" : "$item"
                              },
                              "hidden" : {
                                "type" : "constant",
                                "value" : false
                              },
                              "cssClasses" : {
                                "type" : "constant",
                                "value" : ""
                              },
                              "buttonStyle" : {
                                "type" : "constant",
                                "value" : "danger"
                              },
                              "label" : {
                                "type" : "interpolation",
                                "value" : "<span class=\"glyphicon glyphicon-remove\"></span>"
                              },
                              "dataToSend" : {
                                "type" : "expression"
                              },
                              "labelHidden" : {
                                "type" : "constant",
                                "value" : false
                              },
                              "collectionPosition" : {
                                "type" : "constant",
                                "value" : "Item"
                              },
                              "targetUrlOnSuccess" : {
                                "type" : "interpolation"
                              },
                              "action" : {
                                "type" : "constant",
                                "value" : "Remove from collection"
                              },
                              "collectionToModify" : {
                                "type" : "variable",
                                "value" : "$collection"
                              },
                              "valueToAdd" : {
                                "type" : "expression"
                              },
                              "disabled" : {
                                "type" : "constant",
                                "value" : false
                              },
                              "alignment" : {
                                "type" : "constant",
                                "value" : "right"
                              },
                              "dimension" : {
                                "type" : "constant",
                                "value" : 12
                              }
                            },
                            "reference" : "8fcbf3d8-299a-4c7f-9a6d-94a70d587a0f",
                            "hasValidationError" : false,
                            "id" : "pbButton",
                            "description" : ""
                          }
                        ]
                      ]
                    }
                  ],
                  [
                    {
                      "type" : "component",
                      "dimension" : {
                        "md" : 12,
                        "sm" : 12,
                        "xs" : 12,
                        "lg" : 12
                      },
                      "propertyValues" : {
                        "removeItem" : {
                          "type" : "variable"
                        },
                        "hidden" : {
                          "type" : "constant",
                          "value" : false
                        },
                        "cssClasses" : {
                          "type" : "constant",
                          "value" : ""
                        },
                        "buttonStyle" : {
                          "type" : "constant",
                          "value" : "primary"
                        },
                        "label" : {
                          "type" : "interpolation",
                          "value" : "<span class=\"glyphicon glyphicon-plus\"></span> Add Address"
                        },
                        "dataToSend" : {
                          "type" : "expression"
                        },
                        "labelHidden" : {
                          "type" : "constant",
                          "value" : false
                        },
                        "collectionPosition" : {
                          "type" : "constant"
                        },
                        "targetUrlOnSuccess" : {
                          "type" : "interpolation"
                        },
                        "action" : {
                          "type" : "constant",
                          "value" : "Add to collection"
                        },
                        "collectionToModify" : {
                          "type" : "variable",
                          "value" : "peopleToUpdate.address"
                        },
                        "valueToAdd" : {
                          "type" : "expression",
                          "value" : "{\n  \"persistenceId_string\" : \"\",\n  \"street\" : \"\",\n  \"zipcode\" : \"\",\n  \"city\" : \"\"\n}"
                        },
                        "disabled" : {
                          "type" : "constant",
                          "value" : false
                        },
                        "alignment" : {
                          "type" : "constant",
                          "value" : "left"
                        },
                        "dimension" : {
                          "type" : "constant",
                          "value" : 12
                        }
                      },
                      "reference" : "617330c2-6d5a-48a4-8bb0-327510b01ebd",
                      "hasValidationError" : false,
                      "id" : "pbButton",
                      "description" : ""
                    }
                  ]
                ]
              }
            ],
            [
              {
                "type" : "component",
                "dimension" : {
                  "md" : 12,
                  "sm" : 12,
                  "xs" : 12,
                  "lg" : 12
                },
                "propertyValues" : {
                  "removeItem" : {
                    "type" : "variable"
                  },
                  "hidden" : {
                    "type" : "constant",
                    "value" : false
                  },
                  "cssClasses" : {
                    "type" : "constant",
                    "value" : ""
                  },
                  "buttonStyle" : {
                    "type" : "constant",
                    "value" : "primary"
                  },
                  "label" : {
                    "type" : "interpolation",
                    "value" : "Submit"
                  },
                  "dataToSend" : {
                    "type" : "expression",
                    "value" : "formOutput"
                  },
                  "dataFromError" : {
                    "type" : "variable",
                    "value" : "formOutput._submitError"
                  },
                  "labelHidden" : {
                    "type" : "constant",
                    "value" : false
                  },
                  "collectionPosition" : {
                    "type" : "constant"
                  },
                  "targetUrlOnSuccess" : {
                    "type" : "interpolation",
                    "value" : "{{ origin }}"
                  },
                  "action" : {
                    "type" : "constant",
                    "value" : "Submit task"
                  },
                  "collectionToModify" : {
                    "type" : "variable"
                  },
                  "valueToAdd" : {
                    "type" : "expression"
                  },
                  "disabled" : {
                    "type" : "expression",
                    "value" : "$form.$invalid"
                  },
                  "alignment" : {
                    "type" : "constant",
                    "value" : "center"
                  },
                  "dimension" : {
                    "type" : "constant",
                    "value" : 12
                  },
                  "assign" : {
                    "type" : "constant",
                    "value" : true
                  },
                  "url" : {
                    "type" : "interpolation"
                  },
                  "responseStatusCode" : {
                    "type" : "variable",
                    "value" : ""
                  },
                  "dataFromSuccess" : {
                    "type" : "variable",
                    "value" : ""
                  },
                  "closeOnSuccess" : {
                    "type" : "constant",
                    "value" : false
                  },
                  "modalId" : {
                    "type" : "constant",
                    "value" : ""
                  }
                },
                "reference" : "91b41062-95bb-42ba-bd80-894325eedf6d",
                "hasValidationError" : false,
                "id" : "pbButton",
                "description" : ""
              }
            ],
            [
              {
                "type" : "component",
                "dimension" : {
                  "md" : 12,
                  "sm" : 12,
                  "xs" : 12,
                  "lg" : 12
                },
                "propertyValues" : {
                  "allowHTML" : {
                    "type" : "constant",
                    "value" : true
                  },
                  "allowHtml" : {
                    "type" : "constant",
                    "value" : true
                  },
                  "labelHidden" : {
                    "type" : "constant",
                    "value" : true
                  },
                  "hidden" : {
                    "type" : "expression",
                    "value" : "!formOutput._submitError.message"
                  },
                  "cssClasses" : {
                    "type" : "constant",
                    "value" : "alert alert-danger col-lg-6 col-lg-offset-3"
                  },
                  "label" : {
                    "type" : "interpolation"
                  },
                  "text" : {
                    "type" : "interpolation",
                    "value" : "<strong>Debug message</strong>\n<br/>\n{{formOutput._submitError.message}}\n{{submit_errors_list}}"
                  },
                  "alignment" : {
                    "type" : "constant",
                    "value" : "left"
                  },
                  "dimension" : {
                    "type" : "constant",
                    "value" : 12
                  }
                },
                "reference" : "b9304676-c5ca-46e2-bbca-1fb56401c1a2",
                "hasValidationError" : false,
                "id" : "pbText",
                "description" : ""
              }
            ]
          ]
        }
      }
    ]
  ],
  "assets" : [
    {
      "id" : "b77b9fa9-fbd6-4585-a1ea-4761ad345cca",
      "name" : "localization.json",
      "type" : "json",
      "order" : 0,
      "external" : false
    },
    {
      "id" : "9fc79ed7-96d2-4cf4-a1a8-5401214bcf7e",
      "name" : "style.css",
      "type" : "css",
      "order" : 0,
      "external" : false
    }
  ],
  "inactiveAssets" : [ ],
  "variables" : {
    "task" : {
      "type" : "url",
      "value" : [
        "../API/bpm/userTask/{{taskId}}"
      ],
      "exposed" : false
    },
    "country_query" : {
      "type" : "url",
      "value" : [
        "../API/bdm/businessData/com.company.model.Country?q=find&p=0&c=99"
      ],
      "exposed" : false
    },
    "submit_errors_list" : {
      "type" : "expression",
      "value" : [
        "if($data.formOutput && $data.formOutput._submitError && $data.formOutput._submitError.explanations){",
        "\tconst liElements = $data.formOutput._submitError.explanations",
        "\t\t.filter(cause => cause !== null)",
        "\t\t.map(cause => \"<li>\" + cause + \"</li>\")",
        "\t\t.join('');",
        "\tif(liElements){",
        "\t\treturn \"<ul>\" + liElements + \"</ul>\";",
        "\t}",
        "}"
      ],
      "exposed" : false
    },
    "formOutput" : {
      "type" : "expression",
      "value" : [
        "if( $data.peopleToUpdate ){",
        "\treturn {",
        "\t\t//map peopleToUpdate variable to expected task contract input",
        "\t\tpeopleToUpdateInput: {",
        "\t\t\tpersistenceId_string: $data.entityId,",
        "\t\t\tfirstName: $data.peopleToUpdate.firstName !== undefined ? $data.peopleToUpdate.firstName : null,",
        "\t\t\tlastName: $data.peopleToUpdate.lastName !== undefined ? $data.peopleToUpdate.lastName : null,",
        "\t\t\tbirthDate: $data.peopleToUpdate.birthDate !== undefined ? $data.peopleToUpdate.birthDate : null,",
        "\t\t\taddress: $data.peopleToUpdate.address.map( it => ({",
        "\t\t\t\tpersistenceId_string: it.persistenceId_string !== undefined ? it.persistenceId_string : null,",
        "\t\t\t\tstreet: it.street !== undefined ? it.street : null,",
        "\t\t\t\tzipcode: it.zipcode !== undefined ? it.zipcode : null,",
        "\t\t\t\tcity: it.city !== undefined ? it.city : null,",
        "\t\t\t\tcountry: it.country ? {",
        "\t\t\t\t\tpersistenceId_string: it.country.persistenceId_string !== undefined ? it.country.persistenceId_string : null",
        "\t\t\t\t} : null",
        "\t\t\t}))",
        "\t\t}",
        "\t}",
        "}"
      ],
      "exposed" : false
    },
    "context" : {
      "type" : "url",
      "value" : [
        "../API/bpm/userTask/{{taskId}}/context"
      ],
      "exposed" : false
    },
    "taskId" : {
      "type" : "urlparameter",
      "value" : [
        "id"
      ],
      "exposed" : false
    },
    "entityId" : {
      "type" : "urlparameter",
      "value" : [
        "entity"
      ],
      "exposed" : false
    },
    "searchPeople" : {
      "type" : "businessdata",
      "value" : [
        "{\"displayValue\":\"findByPersistenceId [com.company.model.People]\",\"businessObjectName\":\"People\",\"query\":{\"name\":\"findByPersistenceId\",\"displayName\":\"findByPersistenceId\"},\"id\":\"com.company.model.People\",\"filters\":[{\"name\":\"persistenceId\",\"type\":\"INTEGER\",\"collection\":false,\"value\":\"{{entityId}}\"}],\"pagination\":{\"p\":\"0\",\"c\":\"1\"}}"
      ],
      "exposed" : false
    },
    "peopleToUpdate" : {
      "type" : "expression",
      "value" : [
        "if($data.searchPeople && $data.searchPeople.length > 0){",
        "    return $data.searchPeople[0];",
        "}"
      ],
      "exposed" : false
    },
    "origin" : {
      "type" : "urlparameter",
      "value" : [
        "origin"
      ],
      "exposed" : false
    }
  },
  "hasValidationError" : false,
  "uuid" : "7eca4d66-749a-422b-b36e-a27dd882337e",
  "type" : "form",
  "description" : "Page generated with Bonita UI designer"
}